{
  "type": "pfm:furniture",
  "group": "kitchen",
  "ingredients": [
    {
      "item": "twilightforest:mining_planks"
    },
    {
      "item": "twilightforest:mining_planks"
    },
    {
      "item": "twilightforest:mining_planks"
    },
    {
      "item": "twilightforest:mining_planks"
    },
    {
      "item": "twilightforest:mining_planks"
    },
    {
      "item": "twilightforest:mining_planks"
    },
    {
      "item": "twilightforest:mining_planks"
    },
    {
      "item": "twilightforest:mining_planks"
    },
    {
      "item": "twilightforest:mining_planks"
    }
  ],
  "result": {
    "count": 6,
    "item": "pfm:mining_twilightforest_kitchen_wall_counter"
  }
}